{
  "id": "exam1",
  "title": {
    "nl": "Examen 1",
    "en": "Exam 1",
    "ar": "الامتحان 1"
  },
  "questions": [
    {
      "id": "exam1-q1",
      "image": "exam1/q1.png",
      "text": {
        "nl": "Mag je als bestuurder van een personenauto gebruikmaken van een rijstrook met de aanduiding 'BUS' of 'LIJNBUS'?",
        "en": "As a driver of a passenger car, are you allowed to use a lane marked with 'BUS' or 'LIJNBUS'?",
        "ar": "هل يُسمح لك كسائق سيارة ركاب باستخدام حارة مخصصة للباصات أو حافلات النقل العام؟"
      },
      "type": "multiple",
      "options": [
        {
          "id": "a",
          "label": {
            "nl": "Ja",
            "en": "Yes",
            "ar": "نعم"
          }
        },
        {
          "id": "b",
          "label": {
            "nl": "Nee",
            "en": "No",
            "ar": "لا"
          }
        }
      ],
      "correct": "b",
      "reason": {
        "nl": "Rijbanen met de aanduiding 'BUS' of 'LIJNBUS' worden busbanen genoemd. Als automobilist mag je daar niet rijden.",
        "en": "Lanes marked with 'BUS' or 'LIJNBUS' are called bus lanes. As a car driver, you are not allowed to drive there.",
        "ar": "الحارات المحددة بـ 'BUS' أو 'LIJNBUS' تسمى حارات الحافلات. كسائق سيارة، لا يُسمح لك بالقيادة فيها."
      }
    },
    {
      "id": "exam1-q2",
      "image": "../../assets/exam1/q2.png",
      "text": {
        "nl": "Mag een kind van 12 jaar en 1.30 meter lang gebruik maken van een driepuntsgordel?",
        "en": "Is a 12-year-old child who is 1.30 meters tall allowed to use a three-point seatbelt?",
        "ar": "هل يُسمح لطفل يبلغ من العمر 12 عاماً وطوله 1.30 متر باستخدام حزام الأمان ثلاثي النقاط؟"
      },
      "type": "multiple",
      "options": [
        {
          "id": "a",
          "label": {
            "nl": "Ja",
            "en": "Yes",
            "ar": "نعم"
          }
        },
        {
          "id": "b",
          "label": {
            "nl": "Nee",
            "en": "No",
            "ar": "لا"
          }
        }
      ],
      "correct": "b",
      "reason": {
        "nl": "De grens voor het dragen van een driepuntsgordel ligt op 1,35 meter; daaronder moet gebruik worden gemaakt van een goedgekeurd kinderbeveiligingssysteem, zoals een zitverhoger of een kinderzitje.",
        "en": "The limit for wearing a three-point seatbelt is 1.35 meters; below that, an approved child restraint system must be used, such as a booster seat or child seat.",
        "ar": "حد استخدام حزام الأمان ثلاثي النقاط هو 1.35 متر؛ دون ذلك، يجب استخدام نظام تأمين معتمد للأطفال، مثل مقعد معزز أو مقعد أطفال."
      }
    },
    {
      "id": "exam1-q3",
      "image": "../../assets/exam1/q3.png",
      "text": {
        "nl": "Je wilt rechtdoor. Moet je de hele militaire colonne voor laten gaan?",
        "en": "You want to go straight ahead. Do you have to let the entire military convoy pass?",
        "ar": "تريد الذهاب مباشرة. هل يجب عليك السماح للقافلة العسكرية بأكملها بالمرور؟"
      },
      "type": "multiple",
      "options": [
        {
          "id": "a",
          "label": {
            "nl": "Ja",
            "en": "Yes",
            "ar": "نعم"
          }
        },
        {
          "id": "b",
          "label": {
            "nl": "Nee",
            "en": "No",
            "ar": "لا"
          }
        }
      ],
      "correct": "b",
      "reason": {
        "nl": "Het eerste militaire voertuig is je nog niet gepasseerd en je komt van rechts, dus jij hebt voorrang.",
        "en": "The first military vehicle has not passed you yet and you are coming from the right, so you have priority.",
        "ar": "المركبة العسكرية الأولى لم تمر بعد وأنت قادم من اليمين، لذلك لديك الأولوية."
      }
    },
    {
      "id": "exam1-q4",
      "image": "../../assets/exam1/q4.png",
      "text": {
        "nl": "Mag je hier doorrijden bij groen licht?",
        "en": "Are you allowed to continue here when the light is green?",
        "ar": "هل يُسمح لك بالاستمرار هنا عندما يكون الضوء أخضر؟"
      },
      "type": "multiple",
      "options": [
        {
          "id": "a",
          "label": {
            "nl": "Ja",
            "en": "Yes",
            "ar": "نعم"
          }
        },
        {
          "id": "b",
          "label": {
            "nl": "Nee",
            "en": "No",
            "ar": "لا"
          }
        }
      ],
      "correct": "b",
      "reason": {
        "nl": "Rijd je hier door dan blokkeer je de kruisende weg door de file voor je, en dat mag nooit.",
        "en": "If you continue here, you will block the crossing road due to the traffic jam ahead, and that is never allowed.",
        "ar": "إذا استمريت هنا، ستحجب الطريق المتقاطع بسبب الازدحام المروري أمامك، وهذا غير مسموح به أبداً."
      }
    },
    {
      "id": "exam1-q5",
      "image": "../../assets/exam1/q5.png",
      "text": {
        "nl": "Welk deel van de weg wordt de rijbaan genoemd?",
        "en": "Which part of the road is called the carriageway?",
        "ar": "أي جزء من الطريق يُسمى مسار المركبات؟"
      },
      "type": "multiple",
      "options": [
        {
          "id": "a",
          "label": {
            "nl": "A",
            "en": "A",
            "ar": "A"
          }
        },
        {
          "id": "b",
          "label": {
            "nl": "B",
            "en": "B",
            "ar": "B"
          }
        },
        {
          "id": "c",
          "label": {
            "nl": "C",
            "en": "C",
            "ar": "C"
          }
        }
      ],
      "correct": "b",
      "reason": {
        "nl": "De rijbaan is het gedeelte van de weg dat bestemd is voor rijdende voertuigen.",
        "en": "The carriageway is the part of the road intended for moving vehicles.",
        "ar": "مسار المركبات هو الجزء من الطريق المخصص للمركبات المتحركة."
      }
    },
    {
      "id": "exam1-q6",
      "image": "../../assets/exam1/q6.png",
      "text": {
        "nl": "Wat betekent een groene ventieldop op de band?",
        "en": "What does a green valve cap on the tire mean?",
        "ar": "ماذا يعني غطاء الصمام الأخضر على الإطار؟"
      },
      "type": "multiple",
      "options": [
        {
          "id": "a",
          "label": {
            "nl": "Reserveband",
            "en": "Spare tire",
            "ar": "إطار احتياطي"
          }
        },
        {
          "id": "b",
          "label": {
            "nl": "Zomerband",
            "en": "Summer tire",
            "ar": "إطار صيفي"
          }
        },
        {
          "id": "c",
          "label": {
            "nl": "Een band die gevuld is met stikstof",
            "en": "A tire filled with nitrogen",
            "ar": "إطار مملوء بالنيتروجين"
          }
        }
      ],
      "correct": "c",
      "reason": {
        "nl": "Er wordt een groen ventieldopje gebruikt als de band gevuld is met stikstof.",
        "en": "A green valve cap is used when the tire is filled with nitrogen.",
        "ar": "يُستخدم غطاء صمام أخضر عندما يكون الإطار مملوءاً بالنيتروجين."
      }
    },
    {
      "id": "exam1-q7",
      "image": "../../assets/exam1/q7.png",
      "text": {
        "nl": "Je komt hier aan rijden en wil linksaf slaan. Wat doe je?",
        "en": "You arrive here and want to turn left. What do you do?",
        "ar": "تصل إلى هنا وتريد الانعطاف يساراً. ماذا تفعل؟"
      },
      "type": "multiple",
      "options": [
        {
          "id": "a",
          "label": {
            "nl": "Je wacht voor de haaientanden totdat de grijze auto is afgeslagen",
            "en": "You wait before the yield markings until the gray car has turned",
            "ar": "تنتظر أمام علامات الأولوية حتى تنعطف السيارة الرمادية"
          }
        },
        {
          "id": "b",
          "label": {
            "nl": "Je rijdt door tot het middenstuk en wacht daar tot de grijze auto is afgeslagen",
            "en": "You drive to the center section and wait there until the gray car has turned",
            "ar": "تقود إلى القسم الأوسط وتنتظر هناك حتى تنعطف السيارة الرمادية"
          }
        },
        {
          "id": "c",
          "label": {
            "nl": "Je rijdt door en neemt de afslag voor de grijze auto omdat jij eerst mag",
            "en": "You continue and take the exit before the gray car because you have priority",
            "ar": "تستمر وتأخذ المخرج قبل السيارة الرمادية لأن لديك الأولوية"
          }
        }
      ],
      "correct": "a",
      "reason": {
        "nl": "Rijd je door naar het middenstuk, dan zal je een deel van de weg blokkeren met jouw aanhangwagen. Dit is verboden. Daarnaast heb jij ook geen voorrang, dus wacht je achter de haaientanden totdat de grijze auto is afgeslagen.",
        "en": "If you drive to the center section, you will block part of the road with your trailer. This is prohibited. Additionally, you don't have priority, so you wait behind the yield markings until the gray car has turned.",
        "ar": "إذا قدت إلى القسم الأوسط، ستحجب جزءاً من الطريق بمقطورتك. هذا ممنوع. بالإضافة إلى ذلك، ليس لديك الأولوية، لذلك تنتظر خلف علامات الأولوية حتى تنعطف السيارة الرمادية."
      },
      "category": "lanes"
    },
    {
      "id": "exam1-q8",
      "image": "../../assets/exam1/q8.png",
      "text": {
        "nl": "Is een kentekenplaat noodzakelijk in deze situatie?",
        "en": "Is a license plate necessary in this situation?",
        "ar": "هل لوحة الترخيص ضرورية في هذا الموقف؟"
      },
      "type": "multiple",
      "options": [
        {
          "id": "a",
          "label": {
            "nl": "Ja",
            "en": "Yes",
            "ar": "نعم"
          }
        },
        {
          "id": "b",
          "label": {
            "nl": "Nee",
            "en": "No",
            "ar": "لا"
          }
        }
      ],
      "correct": "a",
      "reason": {
        "nl": "Je kentekenplaat moet ten alle tijde goed zichtbaar en leesbaar zijn.",
        "en": "Your license plate must be clearly visible and legible at all times.",
        "ar": "يجب أن تكون لوحة الترخيص الخاصة بك واضحة ومقروءة في جميع الأوقات."
      }
    },
    {
      "id": "exam1-q9",
      "image": "../../assets/exam1/q9.png",
      "text": {
        "nl": "Je wilt hier rechtdoor. Moet je toch stoppen?",
        "en": "You want to go straight here. Do you still have to stop?",
        "ar": "تريد الذهاب مباشرة هنا. هل يجب عليك التوقف؟"
      },
      "type": "multiple",
      "options": [
        {
          "id": "a",
          "label": {
            "nl": "Ja",
            "en": "Yes",
            "ar": "نعم"
          }
        },
        {
          "id": "b",
          "label": {
            "nl": "Nee",
            "en": "No",
            "ar": "لا"
          }
        }
      ],
      "correct": "b",
      "reason": {
        "nl": "Verkeerslichten gaan boven verkeerstekens die de voorrang regelen.",
        "en": "Traffic lights take precedence over traffic signs that regulate priority.",
        "ar": "إشارات المرور لها الأولوية على اللافتات المرورية التي تنظم حق الأولوية."
      }
    },
    {
      "id": "exam1-q10",
      "image": "../../assets/exam1/q10.png",
      "text": {
        "nl": "Je wilt rechtdoor. Moet je de bromfietser voor laten gaan?",
        "en": "You want to go straight ahead. Do you have to let the moped rider pass?",
        "ar": "تريد الذهاب مباشرة. هل يجب عليك السماح لراكب الدراجة البخارية بالمرور؟"
      },
      "type": "multiple",
      "options": [
        {
          "id": "a",
          "label": {
            "nl": "Ja",
            "en": "Yes",
            "ar": "نعم"
          }
        },
        {
          "id": "b",
          "label": {
            "nl": "Nee",
            "en": "No",
            "ar": "لا"
          }
        }
      ],
      "correct": "b",
      "reason": {
        "nl": "Bestuurders op een onverharde weg moeten voorrang verlenen aan bestuurders op een verharde weg.",
        "en": "Drivers on an unpaved road must yield to drivers on a paved road.",
        "ar": "يجب على السائقين على طريق غير معبد منح الأولوية للسائقين على طريق معبد."
      }
    },
    {
      "id": "exam1-q11",
      "image": "../../assets/exam1/q11.png",
      "text": {
        "nl": "Je wilt linksaf. Moet je stoppen?",
        "en": "You want to turn left. Do you have to stop?",
        "ar": "تريد الانعطاف يساراً. هل يجب عليك التوقف؟"
      },
      "type": "multiple",
      "options": [
        {
          "id": "a",
          "label": {
            "nl": "Ja",
            "en": "Yes",
            "ar": "نعم"
          }
        },
        {
          "id": "b",
          "label": {
            "nl": "Nee",
            "en": "No",
            "ar": "لا"
          }
        }
      ],
      "correct": "a",
      "reason": {
        "nl": "Zie de armen van de verkeersregelaar als slagbomen: die staan nu naar beneden voor jou. Alleen bestuurders op de kruisende weg mogen nu doorrijden.",
        "en": "See the traffic controller's arms as barriers: they are currently down for you. Only drivers on the crossing road may proceed now.",
        "ar": "انظر إلى ذراعي منظم المرور كحواجز: هي الآن للأسفل بالنسبة لك. يمكن فقط للسائقين على الطريق المتقاطع المتابعة الآن."
      }
    },
    {
      "id": "exam1-q12",
      "image": "../../assets/exam1/q12.png",
      "text": {
        "nl": "Wie mag je bij uitstappen niet hinderen?",
        "en": "Who must you not obstruct when getting out?",
        "ar": "من يجب ألا تعيق عند النزول من السيارة؟"
      },
      "type": "multiple",
      "options": [
        {
          "id": "a",
          "label": {
            "nl": "Alleen voetgangers",
            "en": "Only pedestrians",
            "ar": "المشاة فقط"
          }
        },
        {
          "id": "b",
          "label": {
            "nl": "Alleen bestuurders",
            "en": "Only drivers",
            "ar": "السائقون فقط"
          }
        },
        {
          "id": "c",
          "label": {
            "nl": "Bestuurders en voetgangers",
            "en": "Drivers and pedestrians",
            "ar": "السائقون والمشاة"
          }
        }
      ],
      "correct": "c",
      "reason": {
        "nl": "Het in- en uitstappen worden samen als één bijzondere verrichting beschouwd, waarbij je alle weggebruikers voor moet laten gaan.",
        "en": "Getting in and out are considered together as one special maneuver, where you must let all road users pass.",
        "ar": "يعتبر الصعود والنزول معاً كمناورة خاصة واحدة، حيث يجب عليك السماح لجميع مستخدمي الطريق بالمرور."
      }
    },
    {
      "id": "exam1-q13",
      "image": "../../assets/exam1/q13.png",
      "text": {
        "nl": "Wat is je toegestane maximumsnelheid op deze weg? (Km/u)",
        "en": "What is your allowed maximum speed on this road? (Km/h)",
        "ar": "ما هي السرعة القصوى المسموح بها على هذا الطريق؟ (كم/ساعة)"
      },
      "type": "input",
      "options": [],
      "correct": "90",
      "reason": {
        "nl": "Met een aanhangwagen is de maximumsnelheid op de autosnelweg 90 km/u.",
        "en": "With a trailer, the maximum speed on the highway is 90 km/h.",
        "ar": "مع مقطورة، السرعة القصوى على الطريق السريع هي 90 كم/ساعة."
      }
    },
    {
      "id": "exam1-q14",
      "image": "../../assets/exam1/q14.png",
      "text": {
        "nl": "Wat geeft dit verkeersbord aan?",
        "en": "What does this traffic sign indicate?",
        "ar": "ماذا تعني هذه الإشارة المرورية؟"
      },
      "type": "multiple",
      "options": [
        {
          "id": "a",
          "label": {
            "nl": "Verboden in te rijden",
            "en": "No entry",
            "ar": "ممنوع الدخول"
          }
        },
        {
          "id": "b",
          "label": {
            "nl": "Je kruist een voorrangsweg",
            "en": "You are crossing a priority road",
            "ar": "أنت تعبر طريق أولوية"
          }
        },
        {
          "id": "c",
          "label": {
            "nl": "Je nadert een gevaarlijk kruispunt",
            "en": "You are approaching a dangerous intersection",
            "ar": "أنت تقترب من تقاطع خطير"
          }
        }
      ],
      "correct": "c",
      "reason": {
        "nl": "Dit verkeersbord waarschuwt voor het naderen van een gevaarlijk kruispunt. De driehoekige vorm met de punt omhoog duidt op een waarschuwingsbord.",
        "en": "This traffic sign warns of approaching a dangerous intersection. The triangular shape with the point up indicates a warning sign.",
        "ar": "هذه الإشارة المرورية تحذر من الاقتراب من تقاطع خطير. الشكل المثلث مع الرأس لأعلى يشير إلى إشارة تحذير."
      }
    },
    {
      "id": "exam1-q15",
      "image": "../../assets/exam1/q15.png",
      "text": {
        "nl": "Mag de tractor hier 50 km/u rijden?",
        "en": "Is the tractor allowed to drive 50 km/h here?",
        "ar": "هل يُسمح للجرار هنا بالقيادة بسرعة 50 كم/ساعة؟"
      },
      "type": "multiple",
      "options": [
        {
          "id": "a",
          "label": {
            "nl": "Ja",
            "en": "Yes",
            "ar": "نعم"
          }
        },
        {
          "id": "b",
          "label": {
            "nl": "Nee",
            "en": "No",
            "ar": "لا"
          }
        }
      ],
      "correct": "b",
      "reason": {
        "nl": "Met een landbouwvoertuig mag je binnen de bebouwde kom maximaal 25 kilometer per uur rijden.",
        "en": "With an agricultural vehicle, you may drive a maximum of 25 kilometers per hour within built-up areas.",
        "ar": "مع مركبة زراعية، يمكنك القيادة بحد أقصى 25 كيلومتر في الساعة داخل المناطق المأهولة."
      }
    },
    {
      "id": "exam1-q16",
      "image": "../../assets/exam1/q16.png",
      "text": {
        "nl": "Is het ook verplicht om richting aan te geven als je afslaat naar een voorsorteerstrook?",
        "en": "Are you also required to signal when turning into a turning lane?",
        "ar": "هل أنت مُلزم بإعطاء إشارة عند الانعطاف إلى حارة الترتيب المسبق؟"
      },
      "type": "multiple",
      "options": [
        {
          "id": "a",
          "label": {
            "nl": "Ja",
            "en": "Yes",
            "ar": "نعم"
          }
        },
        {
          "id": "b",
          "label": {
            "nl": "Nee",
            "en": "No",
            "ar": "لا"
          }
        }
      ],
      "correct": "b",
      "reason": {
        "nl": "Bestuurders van motorvoertuigen zijn verplicht om richting aan te geven bij een zijdelingse verplaatsing.",
        "en": "Drivers of motor vehicles are required to signal when making a lateral movement.",
        "ar": "سائقو المركبات الآلية ملزمون بإعطاء إشارة عند القيام بحركة جانبية."
      }
    },
    {
      "id": "exam1-q17",
      "image": "../../assets/exam1/q17.png",
      "text": {
        "nl": "Welke hoofdsteun is hier juist afgesteld?",
        "en": "Which headrest is correctly adjusted here?",
        "ar": "أي مسند رأس مضبوط بشكل صحيح هنا؟"
      },
      "type": "multiple",
      "options": [
        {
          "id": "a",
          "label": {
            "nl": "Hoofdsteun A",
            "en": "Headrest A",
            "ar": "مسند الرأس A"
          }
        },
        {
          "id": "b",
          "label": {
            "nl": "Hoofdsteun B",
            "en": "Headrest B",
            "ar": "مسند الرأس B"
          }
        },
        {
          "id": "c",
          "label": {
            "nl": "Geen van beide",
            "en": "Neither",
            "ar": "لا شيء منهما"
          }
        }
      ],
      "correct": "b",
      "reason": {
        "nl": "De bovenkant van de hoofdsteun moet gelijk zijn aan de bovenkant van je hoofd. Zo wordt je hoofd bij een botsing goed en stevig opgevangen.",
        "en": "The top of the headrest should be level with the top of your head. This way, your head is properly and firmly supported in a collision.",
        "ar": "يجب أن يكون أعلى مسند الرأس متساوياً مع أعلى رأسك. بهذه الطريقة، يتم دعم رأسك بشكل صحيح ومتين في حالة الاصطدام."
      }
    },
    {
      "id": "exam1-q18",
      "image": "../../assets/exam1/q18.png",
      "text": {
        "nl": "Je bent bijna aan het einde van de tunnel en er komt ineens rook onder de motorkap vandaan. Wat moet je doen?",
        "en": "You're almost at the end of the tunnel and smoke suddenly comes from under the hood. What should you do?",
        "ar": "أنت على وشك الخروج من النفق وفجأة يظهر دخان من أسفل غطاء المحرك. ماذا يجب أن تفعل؟"
      },
      "type": "multiple",
      "options": [
        {
          "id": "a",
          "label": {
            "nl": "Direct stoppen en de motor uitzetten",
            "en": "Stop immediately and switch off the engine",
            "ar": "تتوقف فوراً وتطفئ المحرك"
          }
        },
        {
          "id": "b",
          "label": {
            "nl": "Je rijdt de tunnel uit en stopt daarna direct",
            "en": "Drive out of the tunnel and then stop immediately",
            "ar": "تخرج من النفق ثم تتوقف فوراً"
          }
        }
      ],
      "correct": "b",
      "reason": {
        "nl": "Het is veiliger om de tunnel uit te rijden en de auto daarna direct aan de kant te zetten.",
        "en": "It is safer to drive out of the tunnel and then immediately pull over.",
        "ar": "من الآمن الخروج من النفق ثم التوقف على جانب الطريق فوراً."
      }
    },
    {
      "id": "exam1-q19",
      "image": "exam1/q19.png",
      "text": {
        "nl": "Wat is de juiste volgorde van voor laten gaan?",
        "en": "What is the correct order of right of way?",
        "ar": "ما هو الترتيب الصحيح للأولوية؟"
      },
      "type": "interactive-choice",
      "options": [],
      "correct": "1. Auto, 2. Fietser, 3. Bromfiets",
      "reason": {
        "nl": "De auto (1) rijdt rechtdoor op een voorrangsweg. De fietser en motor staan achter haaientanden op dezelfde weg. De fietser (2) rijdt rechtdoor en heeft hierdoor voorrang op de afslaande motor (3).",
        "en": "The car (1) is going straight on a priority road. The cyclist and motorcycle are behind yield markings on the same road. The cyclist (2) is going straight and therefore has priority over the turning motorcycle (3).",
        "ar": "السيارة (1) تسير مباشرة على طريق أولوية. راكب الدراجة والدراجة النارية خلف علامات الأولوية على نفس الطريق. راكب الدراجة (2) يسير مباشرة وبالتالي لديه الأولوية على الدراجة النارية المنعطفة (3)."
      },
      "dragTargets": [
        {
          "x": 27,
          "y": 23,
          "id": "cyclist",
          "label": {
            "nl": "Fietser",
            "en": "Cyclist",
            "ar": "راكب الدراجة"
          }
        },
        {
          "x": 95,
          "y": 32,
          "id": "car",
          "label": {
            "nl": "Auto",
            "en": "Car",
            "ar": "سيارة"
          }
        },
        {
          "x": 72,
          "y": 67,
          "id": "moped",
          "label": {
            "nl": "Bromfiets",
            "en": "Moped",
            "ar": "دراجة بخارية"
          }
        }
      ]
    },
    {
      "id": "exam1-q20",
      "image": "../../assets/exam1/q20.png",
      "text": {
        "nl": "Je haalt de brommobiel hier in. Mag dat?",
        "en": "You are overtaking the microcar here. Is that allowed?",
        "ar": "أنت تتجاوز مركبة صغيرة هنا. هل يُسمح بذلك؟"
      },
      "type": "multiple",
      "options": [
        {
          "id": "a",
          "label": {
            "nl": "Ja",
            "en": "Yes",
            "ar": "نعم"
          }
        },
        {
          "id": "b",
          "label": {
            "nl": "Nee",
            "en": "No",
            "ar": "لا"
          }
        }
      ],
      "correct": "b",
      "reason": {
        "nl": "Vlak voor of op een zebrapad mag je andere bestuurders niet inhalen.",
        "en": "Just before or on a pedestrian crossing, you may not overtake other drivers.",
        "ar": "قبل ممر المشاة مباشرة أو عليه، لا يجوز لك تجاوز السائقين الآخرين."
      }
    },
    {
      "id": "exam1-q21",
      "image": "../../assets/exam1/q21.png",
      "text": {
        "nl": "De brug staat open. Moet je de motor uitschakelen?",
        "en": "The bridge is open. Must you switch off the engine?",
        "ar": "الجسر مفتوح. هل يجب عليك إيقاف تشغيل المحرك؟"
      },
      "type": "multiple",
      "options": [
        {
          "id": "a",
          "label": {
            "nl": "Ja",
            "en": "Yes",
            "ar": "نعم"
          }
        },
        {
          "id": "b",
          "label": {
            "nl": "Nee",
            "en": "No",
            "ar": "لا"
          }
        }
      ],
      "correct": "a",
      "reason": {
        "nl": "Na een minuut stilstaan moet je de motor uitschakelen. Dus bij een openstaande brug zet jij de motor uit.",
        "en": "After standing still for a minute, you must switch off the engine. So when a bridge is open, you turn off the engine.",
        "ar": "بعد التوقف لمدة دقيقة، يجب عليك إيقاف تشغيل المحرك. لذا عندما يكون الجسر مفتوحاً، تقوم بإطفاء المحرك."
      }
    },
    {
      "id": "exam1-q22",
      "image": "../../assets/exam1/q22.png",
      "text": {
        "nl": "Moet je de bus hier voor laten gaan?",
        "en": "Do you have to give way to the bus here?",
        "ar": "هل يجب أن تفسح الطريق للحافلة هنا؟"
      },
      "type": "multiple",
      "options": [
        {
          "id": "a",
          "label": {
            "nl": "Ja",
            "en": "Yes",
            "ar": "نعم"
          }
        },
        {
          "id": "b",
          "label": {
            "nl": "Nee",
            "en": "No",
            "ar": "لا"
          }
        }
      ],
      "correct": "b",
      "reason": {
        "nl": "Buiten de bebouwde kom hoef je een bus die de halte verlaat geen voorrang te verlenen. Dit herken je aan de strepen op het wegdek. Deze geven aan dat je op een 80km/u weg rijdt.",
        "en": "Outside built-up areas, you do not have to give priority to a bus leaving a stop. You can recognize this by the markings on the road surface. These indicate that you are driving on an 80 km/h road.",
        "ar": "خارج المناطق المأهولة، لا يجب أن تمنح الأولوية لحافلة تغادر المحطة. يمكنك التعرف على هذا من خلال العلامات على سطح الطريق. هذه تشير إلى أنك تقود على طريق بسرعة 80 كم/ساعة."
      }
    },
    {
      "id": "exam1-q23",
      "image": "../../assets/exam1/q23.png",
      "text": {
        "nl": "De blauwe auto staat tegen de as van de weg voorgesorteerd om links af te slaan. Mag jij de auto van rechts inhalen?",
        "en": "The blue car is positioned near the center line to turn left. Are you allowed to overtake it on the right?",
        "ar": "السيارة الزرقاء متمركزة عند خط الوسط لتنعطف يساراً. هل يُسمح لك بتجاوزها من اليمين؟"
      },
      "type": "multiple",
      "options": [
        {
          "id": "a",
          "label": {
            "nl": "Ja",
            "en": "Yes",
            "ar": "نعم"
          }
        },
        {
          "id": "b",
          "label": {
            "nl": "Nee",
            "en": "No",
            "ar": "لا"
          }
        }
      ],
      "correct": "a",
      "reason": {
        "nl": "Omdat de fietsstrook onderbroken strepen heeft, mag je in deze situatie de afslaande auto rechts inhalen, mits je geen fietsers hindert.",
        "en": "Because the bicycle lane has broken lines, you may overtake the turning car on the right in this situation, provided you do not hinder cyclists.",
        "ar": "لأن حارة الدراجات تحتوي على خطوط متقطعة، يمكنك تجاوز السيارة المنعطفة من اليمين في هذا الموقف، بشرط ألا تعيق راكبي الدراجات."
      }
    },
    {
      "id": "exam1-q24",
      "image": "../../assets/exam1/q24.png",
      "text": {
        "nl": "Wat is het grootste verschil tussen een e-bike en een speed-pedelec?",
        "en": "What is the main difference between an e-bike and a speed-pedelec?",
        "ar": "ما الفرق الأكبر بين الدراجة الكهربائية e‑bike ودراجة السرعة speed‑pedelec؟"
      },
      "type": "multiple",
      "options": [
        {
          "id": "a",
          "label": {
            "nl": "Een e-bike gaat max 25 km/u en een speed-pedelec max 45 km/u",
            "en": "An e‑bike tops at 25 km/h and a speed‑pedelec at 45 km/h",
            "ar": "الدراجة الكهربائية تصل حتى 25 كم/س والـ speed‑pedelec حتى 45 كم/س"
          }
        },
        {
          "id": "b",
          "label": {
            "nl": "Een e-bike gaat max 45 km/u en een speed-pedelec max 25 km/u",
            "en": "An e‑bike tops at 45 km/h and a speed‑pedelec at 25 km/h",
            "ar": "الدراجة الكهربائية تصل حتى 45 كم/س والـ speed‑pedelec حتى 25 كم/س"
          }
        },
        {
          "id": "c",
          "label": {
            "nl": "Er is geen verschil",
            "en": "There is no difference",
            "ar": "لا يوجد فرق"
          }
        }
      ],
      "correct": "a",
      "reason": {
        "nl": "Een speed-pedelec, ook wel high speed e-bike genoemd, gaat sneller dan een gewone e-bike. Voor de speed-pedelec gelden dan ook de bromfietsregels.",
        "en": "A speed-pedelec, also called a high-speed e-bike, goes faster than a regular e-bike. Therefore, the moped rules apply to the speed-pedelec.",
        "ar": "دراجة speed-pedelec، تسمى أيضاً دراجة كهربائية عالية السرعة، أسرع من الدراجة الكهربائية العادية. لذلك، تنطبق قواعد الدراجات البخارية على الـ speed-pedelec."
      }
    },
    {
      "id": "exam1-q25",
      "image": "../../assets/exam1/q25.png",
      "text": {
        "nl": "Je wilt de rotonde verlaten. Moet je de voetganger voor laten gaan?",
        "en": "You want to leave the roundabout. Do you have to yield to the pedestrian?",
        "ar": "تريد الخروج من الدوار. هل يجب أن تفسح الطريق للمشاة؟"
      },
      "type": "multiple",
      "options": [
        {
          "id": "a",
          "label": {
            "nl": "Ja",
            "en": "Yes",
            "ar": "نعم"
          }
        },
        {
          "id": "b",
          "label": {
            "nl": "Nee",
            "en": "No",
            "ar": "لا"
          }
        }
      ],
      "correct": "a",
      "reason": {
        "nl": "Als je een rotonde verlaat, moet je alle weggebruikers die de rotonde nog vervolgen voorlaten. De voetganger blijft de rotonde volgen.",
        "en": "When leaving a roundabout, you must yield to all road users who continue on the roundabout. The pedestrian continues to follow the roundabout.",
        "ar": "عند مغادرة الدوار، يجب أن تفسح الطريق لجميع مستخدمي الطريق الذين يستمرون في الدوار. المشاة يستمرون في متابعة الدوار."
      }
    },
    {
      "id": "exam1-q26",
      "image": "../../assets/exam1/q26.png",
      "text": {
        "nl": "Hoe kun je zo energiezuinig rijden?",
        "en": "How can you drive most fuel-efficiently?",
        "ar": "كيف تقود بأكبر قدر من التوفير في الوقود؟"
      },
      "type": "multiple",
      "options": [
        {
          "id": "a",
          "label": {
            "nl": "Door zoveel mogelijk in de hoogste versnelling te rijden",
            "en": "By driving as much as possible in the highest gear",
            "ar": "بالقيادة قدر الإمكان على أعلى ترس"
          }
        },
        {
          "id": "b",
          "label": {
            "nl": "Door vaart te minderen met de koppeling ingetrapt",
            "en": "By reducing speed with the clutch depressed",
            "ar": "بتقليل السرعة مع ضغط دواسة القابض"
          }
        },
        {
          "id": "c",
          "label": {
            "nl": "Door met een warme motor weg te rijden",
            "en": "By setting off with a warm engine",
            "ar": "بالانطلاق عندما يكون المحرك حاراً"
          }
        }
      ],
      "correct": "a",
      "reason": {
        "nl": "Door snel op te schakelen en in een hoge versnelling te rijden, rijd je zuinig.",
        "en": "By shifting up quickly and driving in a high gear, you drive fuel-efficiently.",
        "ar": "بالتبديل إلى ترس أعلى بسرعة والقيادة بترس عالٍ، تقود بتوفير للوقود."
      }
    },
    {
      "id": "exam1-q27",
      "image": "../../assets/exam1/q27.png",
      "text": {
        "nl": "Kun je hier een tegemoetkomende motor verwachten?",
        "en": "Can you expect an oncoming motorcycle here?",
        "ar": "هل يمكنك توقع قدوم دراجة نارية مقابلة هنا؟"
      },
      "type": "multiple",
      "options": [
        {
          "id": "a",
          "label": {
            "nl": "Ja",
            "en": "Yes",
            "ar": "نعم"
          }
        },
        {
          "id": "b",
          "label": {
            "nl": "Nee",
            "en": "No",
            "ar": "لا"
          }
        }
      ],
      "correct": "b",
      "reason": {
        "nl": "Op deze éénrichtingsweg kun je geen motorvoertuigen vanuit de tegengestelde richting verwachten.",
        "en": "On this one-way road, you cannot expect motor vehicles from the opposite direction.",
        "ar": "على هذا الطريق أحادي الاتجاه، لا يمكنك توقع مركبات آلية من الاتجاه المعاكس."
      }
    },
    {
      "id": "exam1-q28",
      "image": "../../assets/exam1/q28.png",
      "text": {
        "nl": "Wat betekent dit bord?",
        "en": "What does this sign mean?",
        "ar": "ماذا تعني هذه الإشارة؟"
      },
      "type": "multiple",
      "options": [
        {
          "id": "a",
          "label": {
            "nl": "Voorrangskruispunt",
            "en": "Priority intersection",
            "ar": "تقاطع أولوية"
          }
        },
        {
          "id": "b",
          "label": {
            "nl": "Voorrangsweg",
            "en": "Priority road",
            "ar": "طريق ذو أولوية"
          }
        },
        {
          "id": "c",
          "label": {
            "nl": "Verleen voorrang aan bestuurders op de kruisende weg",
            "en": "Give way to drivers on the crossing road",
            "ar": "أعطِ أولوية لمستخدمي الطريق على الطريق المتقاطع"
          }
        }
      ],
      "correct": "b",
      "reason": {
        "nl": "Dit verkeersbord geeft aan dat je op een voorrangsweg rijdt.",
        "en": "This traffic sign indicates that you are on a priority road.",
        "ar": "هذه الإشارة المرورية تشير إلى أنك على طريق ذي أولوية."
      }
    },
    {
      "id": "exam1-q29",
      "image": "../../assets/exam1/q29.png",
      "text": {
        "nl": "Je rijdt in een dieselauto met emissieklasse 3. Mag je deze milieuzone inrijden?",
        "en": "You are driving a diesel car with emission class 3. Are you allowed to enter this environmental zone?",
        "ar": "أنت تقود سيارة ديزل من فئة الانبعاثات 3. هل يُسمح لك بدخول هذه المنطقة البيئية؟"
      },
      "type": "multiple",
      "options": [
        {
          "id": "a",
          "label": {
            "nl": "Ja",
            "en": "Yes",
            "ar": "نعم"
          }
        },
        {
          "id": "b",
          "label": {
            "nl": "Nee",
            "en": "No",
            "ar": "لا"
          }
        }
      ],
      "correct": "b",
      "reason": {
        "nl": "Je mag deze milieuzone alleen inrijden als je voertuig een emissieklasse van 4 of hoger heeft. Hoe hoger de emissieklasse, hoe schoner het voertuig. Emissieklasse 3 is dus niet schoon genoeg om deze zone in te mogen.",
        "en": "You may only enter this environmental zone if your vehicle has an emission class of 4 or higher. The higher the emission class, the cleaner the vehicle. So emission class 3 is not clean enough to enter this zone.",
        "ar": "يمكنك دخول هذه المنطقة البيئية فقط إذا كانت مركبتك من فئة الانبعاثات 4 أو أعلى. كلما زادت فئة الانبعاثات، كانت المركبة أنظف. لذا فئة الانبعاثات 3 ليست نظيفة بما يكفي لدخول هذه المنطقة."
      }
    },
    {
      "id": "exam1-q30",
      "image": "../../assets/exam1/q30.png",
      "text": {
        "nl": "Gelden op een Y-splitsing dezelfde voorrangsregels als op een volledig kruispunt?",
        "en": "Do the same right-of-way rules apply at a Y-junction as at a full intersection?",
        "ar": "هل تُطبق نفس قواعد الأولوية في تقاطع على شكل Y كما في التقاطع الكامل؟"
      },
      "type": "multiple",
      "options": [
        {
          "id": "a",
          "label": {
            "nl": "Ja",
            "en": "Yes",
            "ar": "نعم"
          }
        },
        {
          "id": "b",
          "label": {
            "nl": "Nee",
            "en": "No",
            "ar": "لا"
          }
        }
      ],
      "correct": "a",
      "reason": {
        "nl": "Een T-splitsing of Y-splitsing zonder voorrangsborden of verkeerstekens is gewoon gelijkwaardig; de gebruikelijke voorrangsregels blijven daar van kracht.",
        "en": "A T-junction or Y-junction without priority signs or road markings is simply equal; the usual right-of-way rules apply there.",
        "ar": "التقاطع على شكل T أو Y بدون لافتات أولوية أو علامات طرق يكون متساوياً؛ تنطبق فيه قواعد الأولوية المعتادة."
      }
    },
    {
      "id": "exam1-q31",
      "image": "../../assets/exam1/q31.png",
      "text": {
        "nl": "Mistlichten aan de voorkant mogen gevoerd worden bij mist, regen of sneeuwval als het zicht minder is dan hoeveel meter?",
        "en": "Front fog lights may be used in fog, rain or snowfall when visibility is less than how many meters?",
        "ar": "يمكن استخدام مصابيح الضباب الأمامية في الضباب أو المطر أو تساقط الثلوج عندما تقل الرؤية عن كم متراً؟"
      },
      "type": "input",
      "options": [],
      "correct": "200",
      "reason": {
        "nl": "Het mistlicht aan de voorkant mag je alleen gebruiken als het zicht door mist, sneeuwval of regen minder is dan 200 meter.",
        "en": "You may only use the front fog light when visibility is less than 200 meters due to fog, snowfall or rain.",
        "ar": "يمكنك استخدام مصباح الضباب الأمامي فقط عندما تكون الرؤية أقل من 200 متر due to الضباب أو تساقط الثلوج أو المطر."
      }
    },
    {
      "id": "exam1-q32",
      "image": "../../assets/exam1/q32.png",
      "text": {
        "nl": "Mag je hier 130 km/u rijden?",
        "en": "Are you allowed to drive 130 km/h here?",
        "ar": "هل يُسمح لك بالقيادة بسرعة 130 كم/س هنا؟"
      },
      "type": "multiple",
      "options": [
        {
          "id": "a",
          "label": {
            "nl": "Ja",
            "en": "Yes",
            "ar": "نعم"
          }
        },
        {
          "id": "b",
          "label": {
            "nl": "Nee",
            "en": "No",
            "ar": "لا"
          }
        }
      ],
      "correct": "b",
      "reason": {
        "nl": "Rij bij slecht weer uit veiligheid langzamer dan de maximumsnelheid.",
        "en": "Drive slower than the maximum speed for safety in bad weather.",
        "ar": "قد بسرعة أقل من السرعة القصوى for safety في الطقس السيء."
      }
    },
    {
      "id": "exam1-q33",
      "image": "../../assets/exam1/q33.png",
      "text": {
        "nl": "Mag je hier inrijden?",
        "en": "Are you allowed to enter here?",
        "ar": "هل يُسمح لك بالدخول هنا؟"
      },
      "type": "multiple",
      "options": [
        {
          "id": "a",
          "label": {
            "nl": "Ja",
            "en": "Yes",
            "ar": "نعم"
          }
        },
        {
          "id": "b",
          "label": {
            "nl": "Nee",
            "en": "No",
            "ar": "لا"
          }
        }
      ],
      "correct": "a",
      "reason": {
        "nl": "Het verkeersbord geeft een doodlopende weg aan, maar inrijden is wel toegestaan.",
        "en": "The traffic sign indicates a dead-end road, but entering is allowed.",
        "ar": "الإشارة المرورية تشير إلى طريق مسدود، لكن الدخول مسموح."
      }
    },
    {
      "id": "exam1-q34",
      "image": "../../assets/exam1/q34.png",
      "text": {
        "nl": "Hoe snel mag je hier rijden? (Km/u)",
        "en": "How fast are you allowed to drive here? (km/h)",
        "ar": "ما السرعة المسموح بها هنا؟ (كم/ساعة)"
      },
      "type": "input",
      "options": [],
      "correct": "50",
      "reason": {
        "nl": "Je rijdt binnen de bebouwde kom, waar de maximumsnelheid voor auto's en motoren 50 km/u is.",
        "en": "You are driving within a built-up area, where the maximum speed for cars and motorcycles is 50 km/h.",
        "ar": "أنت تقود داخل منطقة مأهولة، حيث السرعة القصوى للسيارات والدراجات النارية هي 50 كم/ساعة."
      }
    },
    {
      "id": "exam1-q35",
      "image": "../../assets/exam1/q35.png",
      "text": {
        "nl": "Je ziet geen verkeer naderen. Moet je stoppen?",
        "en": "You see no traffic approaching. Must you stop?",
        "ar": "لا ترى حركة مرور قادمة. هل يجب أن تتوقف؟"
      },
      "type": "multiple",
      "options": [
        {
          "id": "a",
          "label": {
            "nl": "Ja",
            "en": "Yes",
            "ar": "نعم"
          }
        },
        {
          "id": "b",
          "label": {
            "nl": "Nee",
            "en": "No",
            "ar": "لا"
          }
        }
      ],
      "correct": "a",
      "reason": {
        "nl": "De bestuurder nadert hier een stopbord. Bij een stopbord ben je altijd verplicht te stoppen, ook als er geen andere weggebruikers in zicht zijn.",
        "en": "The driver is approaching a stop sign. At a stop sign, you are always required to stop, even if there are no other road users in sight.",
        "ar": "السائق يقترب من إشارة توقف. عند إشارة توقف، يجب عليك دائماً التوقف، حتى لو لم يكن هناك مستخدمي طريق آخرين في الأفق."
      }
    },
    {
      "id": "exam1-q36",
      "image": "../../assets/exam1/q36.png",
      "text": {
        "nl": "Door de sneeuw is je nummerplaat bedekt. Mag je zo rijden?",
        "en": "Your license plate is covered by snow. Are you allowed to drive like this?",
        "ar": "لوحة تسجيلك مغطاة بالثلج. هل يجوز لك القيادة هكذا؟"
      },
      "type": "multiple",
      "options": [
        {
          "id": "a",
          "label": {
            "nl": "Ja",
            "en": "Yes",
            "ar": "نعم"
          }
        },
        {
          "id": "b",
          "label": {
            "nl": "Nee",
            "en": "No",
            "ar": "لا"
          }
        }
      ],
      "correct": "b",
      "reason": {
        "nl": "Het kenteken moet te allen tijde goed leesbaar zijn.",
        "en": "The license plate must be clearly legible at all times.",
        "ar": "يجب أن تكون لوحة الترخيص قابلة للقراءة بوضوح في جميع الأوقات."
      }
    },
    {
      "id": "exam1-q37",
      "image": "../../assets/exam1/q37.png",
      "text": {
        "nl": "Wanneer krijg je als beginnende bestuurder direct een rijverbod opgelegd?",
        "en": "As a novice driver, when do you immediately receive a driving ban?",
        "ar": "متى يُفرض عليك كقائد مبتدئ حظر قيادة مباشرة؟"
      },
      "type": "multiple",
      "options": [
        {
          "id": "a",
          "label": {
            "nl": "Bij meer dan 0,2 promille",
            "en": "> 0.2 ‰",
            "ar": "> 0.2 ‰"
          }
        },
        {
          "id": "b",
          "label": {
            "nl": "Bij meer than 0,4 promille",
            "en": "> 0.4 ‰",
            "ar": "> 0.4 ‰"
          }
        },
        {
          "id": "c",
          "label": {
            "nl": "Bij meer dan 0,5 promille",
            "en": "> 0.5 ‰",
            "ar": "> 0.5 ‰"
          }
        }
      ],
      "correct": "a",
      "reason": {
        "nl": "Een rijverbod wordt opgelegd aan beginnende bestuurders met een alcoholgehalte vanaf 0,2 promille.",
        "en": "A driving ban is imposed on novice drivers with an alcohol level from 0.2 per mille.",
        "ar": "يُفرض حظر القيادة على السائقين المبتدئين بمستوى كحول من 0.2 في الألف."
      }
    },
    {
      "id": "exam1-q38",
      "image": "../../assets/exam1/q38.png",
      "text": {
        "nl": "Nader je hier een spoorwegovergang met een dubbel spoor?",
        "en": "Are you approaching a railway crossing with double tracks here?",
        "ar": "هل تقترب هنا من معبر سكة حديد بمسارين؟"
      },
      "type": "multiple",
      "options": [
        {
          "id": "a",
          "label": {
            "nl": "Ja",
            "en": "Yes",
            "ar": "نعم"
          }
        },
        {
          "id": "b",
          "label": {
            "nl": "Nee",
            "en": "No",
            "ar": "لا"
          }
        }
      ],
      "correct": "b",
      "reason": {
        "nl": "Één kruis staat voor enkel spoor.",
        "en": "One cross stands for single track.",
        "ar": "صليب واحد يمثل مساراً واحداً."
      }
    },
    {
      "id": "exam1-q39",
      "image": "../../assets/exam1/q39.png",
      "text": {
        "nl": "Wie mag er als eerst?",
        "en": "Who has priority first?",
        "ar": "من له الأسبقية أولاً؟"
      },
      "type": "interactive-choice",
      "options": [],
      "correct": "1. Tram, 2. Auto",
      "reason": {
        "nl": "De tram heeft altijd voorrang, behalve als deze van rechts komt. Daarna heeft de auto voorrang omdat deze van rechts komt ten opzichte van de andere auto.",
        "en": "The tram always has priority, except when it comes from the right. Then the car has priority because it comes from the right relative to the other car.",
        "ar": "الترام دائماً له الأولوية، إلا إذا جاء من اليمين. ثم السيارة لها الأولوية لأنها تأتي من اليمين بالنسبة للسيارة الأخرى."
      },
      "dragTargets": [
        {
          "x": 27,
          "y": 78,
          "id": "Tram",
          "label": {
            "nl": "Tram",
            "en": "Tram",
            "ar": "ترام"
          }
        },
        {
          "x": 95,
          "y": 32,
          "id": "Auto",
          "label": {
            "nl": "Auto",
            "en": "Car",
            "ar": "سيارة"
          }
        }
        
      ]
    },
    {
      "id": "exam1-q40",
      "image": "../../assets/exam1/q40.png",
      "text": {
        "nl": "Je merkt dat je door de flinke regenval grip op de weg verliest met je banden. Wat moet je doen?",
        "en": "Due to heavy rain you lose grip with your tires. What should you do?",
        "ar": "بسبب الأمطار الغزيرة تفقد إطاراتك التماسك. ماذا يجب أن تفعل؟"
      },
      "type": "multiple",
      "options": [
        {
          "id": "a",
          "label": {
            "nl": "Je laat het gas los",
            "en": "Ease off the accelerator",
            "ar": "ارفع قدمك عن دواسة الوقود"
          }
        },
        {
          "id": "b",
          "label": {
            "nl": "Je trapt de rem in",
            "en": "Hit the brakes",
            "ar": "تضغط الفرامل"
          }
        },
        {
          "id": "c",
          "label": {
            "nl": "Je geeft gas bij",
            "en": "Accelerate",
            "ar": "تزيد السرعة"
          }
        }
      ],
      "correct": "a",
      "reason": {
        "nl": "Bij aquaplaning is het belangrijk om weer grip op de weg te krijgen. Dat doe je door geleidelijk je snelheid te verlagen.",
        "en": "In aquaplaning, it is important to regain grip on the road. You do this by gradually reducing your speed.",
        "ar": "في الانزلاق المائي، من المهم استعادة التماسك على الطريق. تفعل ذلك عن طريق تقليل سرعتك تدريجياً."
      }
    },
    {
      "id": "exam1-q41",
      "image": "../../assets/exam1/q41.png",
      "text": {
        "nl": "Je stopt hier om een passagier uit te laten stappen. Mag dat?",
        "en": "You stop here to let a passenger get out. Is that allowed?",
        "ar": "تتوقف هنا لإنزال راكب. هل هذا مسموح؟"
      },
      "type": "multiple",
      "options": [
        {
          "id": "a",
          "label": {
            "nl": "Ja",
            "en": "Yes",
            "ar": "نعم"
          }
        },
        {
          "id": "b",
          "label": {
            "nl": "Nee",
            "en": "No",
            "ar": "لا"
          }
        }
      ],
      "correct": "b",
      "reason": {
        "nl": "Op een fietsstrook is het niet toegestaan om stil te staan.",
        "en": "It is not allowed to stand still on a bicycle lane.",
        "ar": "لا يُسمح بالوقوف على حارة الدراجات."
      }
    },
    {
      "id": "exam1-q42",
      "image": "../../assets/exam1/q42.png",
      "text": {
        "nl": "Wat verstaan we onder het verkeer?",
        "en": "What do we mean by 'traffic'?",
        "ar": "ماذا نعني بـ 'حركة المرور'؟"
      },
      "type": "multiple",
      "options": [
        {
          "id": "a",
          "label": {
            "nl": "Bestuurders van een motorvoertuig",
            "en": "Drivers of motor vehicles",
            "ar": "سائقو المركبات الآلية"
          }
        },
        {
          "id": "b",
          "label": {
            "nl": "Alle weggebruikers",
            "en": "All road users",
            "ar": "جميع مستخدمي الطريق"
          }
        },
        {
          "id": "c",
          "label": {
            "nl": "Bestuurders van motorvoertuigen en niet-motorvoertuigen",
            "en": "Drivers of motor and non-motor vehicles",
            "ar": "سائقو المركبات الآلية وغير الآلية"
          }
        }
      ],
      "correct": "b",
      "reason": {
        "nl": "Met 'verkeer' bedoelen we iedereen die aan het verkeer deelneemt; dit omvat alle weggebruikers.",
        "en": "By 'traffic' we mean everyone who participates in traffic; this includes all road users.",
        "ar": "بـ 'حركة المرور' نعني كل من يشارك في حركة المرور؛ وهذا يشمل جميع مستخدمي الطريق."
      }
    },
    {
      "id": "exam1-q43",
      "image": "../../assets/exam1/q43.png",
      "text": {
        "nl": "Je rijdt hier met grootlicht. Mag dat?",
        "en": "You are driving with high beams. Is that allowed?",
        "ar": "أنت تقود بأضواء الطريق (العالية). هل هذا مسموح؟"
      },
      "type": "multiple",
      "options": [
        {
          "id": "a",
          "label": {
            "nl": "Ja",
            "en": "Yes",
            "ar": "نعم"
          }
        },
        {
          "id": "b",
          "label": {
            "nl": "Nee",
            "en": "No",
            "ar": "لا"
          }
        }
      ],
      "correct": "a",
      "reason": {
        "nl": "Grootlicht mag je voeren als het nacht is en je niemand verblindt.",
        "en": "You may use high beams when it is night and you do not dazzle anyone.",
        "ar": "يمكنك استخدام الأضواء العالية عندما يكون الليل ولا تعمي أي شخص."
      }
    },
    {
      "id": "exam1-q44",
      "image": "../../assets/exam1/q44.png",
      "text": {
        "nl": "Je staat hier stil om te laden. Mag dat?",
        "en": "You are standing still here to load. Is that allowed?",
        "ar": "أنت متوقف هنا للتحميل. هل هذا مسموح؟"
      },
      "type": "multiple",
      "options": [
        {
          "id": "a",
          "label": {
            "nl": "Ja",
            "en": "Yes",
            "ar": "نعم"
          }
        },
        {
          "id": "b",
          "label": {
            "nl": "Nee",
            "en": "No",
            "ar": "لا"
          }
        }
      ],
      "correct": "b",
      "reason": {
        "nl": "Laden en lossen is toegestaan binnen een woonerf buiten de parkeervakken.",
        "en": "Loading and unloading is allowed within a residential area outside parking spaces.",
        "ar": "التحميل والتفريغ مسموح به داخل منطقة سكنية خارج أماكن الوقوف."
      }
    },
    {
      "id": "exam1-q45",
      "image": "../../assets/exam1/q45.png",
      "text": {
        "nl": "Een tegenligger haalt in. Je denkt dat hij het niet haalt. Wat doe je?",
        "en": "An oncoming driver is overtaking. You think they won't make it. What do you do?",
        "ar": "سائق قادم في الجهة المقابلة يقوم بالتجاوز. تعتقد أنه لن ينجح. ماذا تفعل؟"
      },
      "type": "multiple",
      "options": [
        {
          "id": "a",
          "label": {
            "nl": "De berm insturen terwijl je hard remt",
            "en": "Steer into the shoulder while braking hard",
            "ar": "تتجه إلى كتف الطريق وأنت تكبح بقوة"
          }
        },
        {
          "id": "b",
          "label": {
            "nl": "De tegenligger waarschuwen met een lichtsignaal",
            "en": "Warn the oncoming driver with a light signal",
            "ar": "تحذر السائق المقابل بإشارة ضوئية"
          }
        },
        {
          "id": "c",
          "label": {
            "nl": "Snelheid verminderen en zoveel mogelijk rechts rijden",
            "en": "Reduce speed and keep as far right as possible",
            "ar": "تُخفّض السرعة وتسير قدر الإمكان إلى اليمين"
          }
        }
      ],
      "correct": "c",
      "reason": {
        "nl": "Het is veilig om je snelheid te verminderen en zoveel mogelijk rechts te rijden bij een tegenligger die inhaalt op jouw weghelft.",
        "en": "It is safe to reduce your speed and drive as far to the right as possible when an oncoming driver is overtaking on your side of the road.",
        "ar": "من الآمن تقليل سرعتك والقيادة بأقصى يمين ممكن عندما يقوم سائق مقابِل بالتجاوز على جانبك من الطريق."
      }
    },
    {
      "id": "exam1-q46",
      "image": "../../assets/exam1/q46.png",
      "text": {
        "nl": "Wat is de juiste volgorde van voor laten gaan?",
        "en": "What is the correct order of right of way?",
        "ar": "ما هو الترتيب الصحيح للأولوية؟"
      },
      "type": "interactive-choice",
      "options": [],
      "correct": "1. Motor, 2. Auto, 3. Bromfiets",
      "reason": {
        "nl": "De auto komt van rechts ten opzichte van de bromfiets. Echter, de auto slaat af naar dezelfde weg als de motor, waarbij de motor de korte bocht heeft. Daarom gaat de motor eerst, gevolgd door de auto, en als laatste de bromfiets.",
        "en": "The car comes from the right relative to the moped. However, the car turns onto the same road as the motorcycle, with the motorcycle having the short turn. Therefore, the motorcycle goes first, followed by the car, and finally the moped.",
        "ar": "السيارة تأتي من اليمين بالنسبة للدراجة البخارية. ومع ذلك، تنعطف السيارة إلى نفس طريق الدراجة النارية، حيث يكون للدراجة النارية المنعطف القصير. لذلك، تذهب الدراجة النارية أولاً، تليها السيارة، وأخيراً الدراجة البخارية."
      }
    },
    {
      "id": "exam1-q47",
      "image": "../../assets/exam1/q47.png",
      "text": {
        "nl": "Je parkeert hier. Mag dat?",
        "en": "You are parking here. Is that allowed?",
        "ar": "أنت توقف سيارتك هنا. هل هذا مسموح؟"
      },
      "type": "multiple",
      "options": [
        {
          "id": "a",
          "label": {
            "nl": "Ja",
            "en": "Yes",
            "ar": "نعم"
          }
        },
        {
          "id": "b",
          "label": {
            "nl": "Nee",
            "en": "No",
            "ar": "لا"
          }
        }
      ],
      "correct": "a",
      "reason": {
        "nl": "Je mag niet buiten de parkeervakken parkeren aan de kant van de weg waar dit verkeersbord staat.",
        "en": "You may not park outside parking spaces on the side of the road where this traffic sign is located.",
        "ar": "لا يجوز لك الوقوف خارج أماكن الوقوف على جانب الطريق حيث توجد هذه الإشارة المرورية."
      }
    },
    {
      "id": "exam1-q48",
      "image": "../../assets/exam1/q48.png",
      "text": {
        "nl": "Je rijdt in de ondergaande zon, die fel in de ogen van tegenliggers schijnt. Wat moet je in dit geval doen?",
        "en": "You are driving in the setting sun, which shines brightly in the eyes of oncoming drivers. What should you do?",
        "ar": "أنت تقود وقت غروب الشمس الذي يسطع بقوة في أعين القادمين من الاتجاه المقابل. ماذا تفعل؟"
      },
      "type": "multiple",
      "options": [
        {
          "id": "a",
          "label": {
            "nl": "Je zet je grootlicht aan",
            "en": "Turn on high beams",
            "ar": "تشغّل الأضواء العالية"
          }
        },
        {
          "id": "b",
          "label": {
            "nl": "Je zet je dimlicht aan",
            "en": "Turn on dipped headlights",
            "ar": "تشغّل الأضواء الواطئة"
          }
        },
        {
          "id": "c",
          "label": {
            "nl": "Je zet je mistlicht aan",
            "en": "Turn on fog lights",
            "ar": "تشغّل أضواء الضباب"
          }
        }
      ],
      "correct": "b",
      "reason": {
        "nl": "Je voert je dimlicht; daarmee zorg je dat je beter zichtbaar bent. Groot licht mag je overdag niet gebruiken en ook niet bij tegenliggend verkeer. Mistlicht gebruik je alleen bij extreem slecht zicht, tot maximaal 50 meter.",
        "en": "You use your dipped headlights; this ensures you are more visible. You may not use high beams during the day or with oncoming traffic. Fog lights are only used in extremely poor visibility, up to 50 meters.",
        "ar": "تستخدم الأضواء الواطئة؛ هذا يضمن أن تكون أكثر وضوحاً. لا يمكنك استخدام الأضواء العالية during the day أو مع حركة المرور القادمة. تُستخدم أضواء الضباب only في الرؤية السيئة للغاية، حتى 50 متراً."
      }
    },
    {
      "id": "exam1-q49",
      "image": "../../assets/exam1/q49.png",
      "text": {
        "nl": "Je neemt de derde afslag. Waar geef je richting aan naar rechts?",
        "en": "You take the third exit. Where do you indicate right?",
        "ar": "ستأخذ المخرج الثالث. أين تُشير إلى اليمين؟"
      },
      "type": "multiple",
      "options": [
        {
          "id": "a",
          "label": {
            "nl": "Punt A",
            "en": "Point A",
            "ar": "النقطة A"
          }
        },
        {
          "id": "b",
          "label": {
            "nl": "Punt B",
            "en": "Point B",
            "ar": "النقطة B"
          }
        }
      ],
      "correct": "b",
      "reason": {
        "nl": "Vlak voordat je afslaat geef je je richting aan.",
        "en": "You indicate your direction just before you turn.",
        "ar": "تشير إلى اتجاهك قبل أن تنعطف مباشرة."
      }
    },
    {
      "id": "exam1-q50",
      "image": "../../assets/exam1/q50.png",
      "text": {
        "nl": "Je neemt de derde afslag. Sorteer je zo goed voor?",
        "en": "You take the third exit. Are you positioning correctly?",
        "ar": "ستأخذ المخرج الثالث. هل تتموضع بشكل صحيح؟"
      },
      "type": "multiple",
      "options": [
        {
          "id": "a",
          "label": {
            "nl": "Ja",
            "en": "Yes",
            "ar": "نعم"
          }
        },
        {
          "id": "b",
          "label": {
            "nl": "Nee",
            "en": "No",
            "ar": "لا"
          }
        }
      ],
      "correct": "b",
      "reason": {
        "nl": "Omdat je de derde afslag wilt nemen zul je op de linkerrijstrook moeten voorsorteren.",
        "en": "Because you want to take the third exit, you should position yourself in the left lane.",
        "ar": "لأنك تريد أخذ المخرج الثالث، يجب أن تتمركز في الحارة اليسرى."
      }
    }
  ]
}